autology/__init__.py
autology/configuration.py
autology/logging.py
autology/publishing.py
autology/storage.py
autology/topics.py
autology/commands/__init__.py
autology/commands/main.py
autology/commands/subcommands/__init__.py
autology/commands/subcommands/dump_config.py
autology/commands/subcommands/export_log_templates.py
autology/commands/subcommands/generate.py
autology/commands/subcommands/initialize.py
autology/commands/subcommands/inject.py
autology/commands/subcommands/make_note.py
autology/commands/subcommands/mkl_project.py
autology/commands/subcommands/serve.py
autology/commands/subcommands/update.py
autology/commands/subcommands/updaters/__init__.py
autology/commands/subcommands/updaters/update_0_1_0_agent_information.py
autology/commands/subcommands/updaters/update_0_2_0_date_time_values.py
autology/reports/__init__.py
autology/reports/index.py
autology/reports/models.py
autology/reports/simple.py
autology/reports/exercise/__init__.py
autology/reports/exercise/exercise.py
autology/reports/exercise/injector.py
autology/reports/exercise/template.py
autology/reports/project/__init__.py
autology/reports/project/injector.py
autology/reports/project/project.py
autology/reports/project/template.py
autology/reports/project/template/__init__.py
autology/reports/project/template/project_base.py
autology/reports/project/template/project_yaml.py
autology/reports/timeline/__init__.py
autology/reports/timeline/keys.py
autology/reports/timeline/template.py
autology/reports/timeline/timeline.py
autology/reports/timeline/processors/__init__.py
autology/reports/timeline/processors/markdown.py
autology/reports/timeline/processors/yaml_processor.py
autology/utilities/__init__.py
autology/utilities/injectors.py
autology/utilities/log_file.py
autology/utilities/plugins.py
autology/utilities/templates.py
autology/utilities/processors/__init__.py
autology/utilities/processors/markdown.py
autology/utilities/processors/yaml.py
autology-0.4.0.dist-info/DESCRIPTION.rst
autology-0.4.0.dist-info/METADATA
autology-0.4.0.dist-info/RECORD
autology-0.4.0.dist-info/WHEEL
autology-0.4.0.dist-info/entry_points.txt
autology-0.4.0.dist-info/metadata.json
autology-0.4.0.dist-info/top_level.txt
