Metadata-Version: 2.0
Name: autology
Version: 0.4.0
Summary: File-based life log
Home-page: https://github.com/MeerkatLabs/autology/
Author: Robert Robinson
Author-email: rerobins@meerkatlabs.org
License: MIT
Platform: UNKNOWN
Classifier: Environment :: Console
Classifier: Development Status :: 3 - Alpha
Classifier: Programming Language :: Python :: 3.6
Classifier: License :: OSI Approved :: MIT License
Classifier: Topic :: Text Processing
Requires-Python: >=3.6, <4
Requires-Dist: dict-recursive-update (<2,>=1.0.0)
Requires-Dist: Jinja2 (<3,>=2.9.6)
Requires-Dist: Markdown (<3,>=2.6.9)
Requires-Dist: munch (<3,>=2.2.0)
Requires-Dist: Pypubsub (<5,>=4.0.0)
Requires-Dist: python-frontmatter (<0.5,>=0.4.2)
Requires-Dist: PyYAML (<4,>=3.12)
Requires-Dist: requests (>=2.18.4)
Requires-Dist: GitPython (>=2.1.7<3)
Requires-Dist: pytz (>=2017.3<2018)
Requires-Dist: tzlocal (>=1.5.1<2)
Requires-Dist: semantic-version (>=2.6.0<3)
Requires-Dist: gpxpy (>=1.1.2<2)
Provides-Extra: dev
Requires-Dist: pylint (>=1.7.4); extra == 'dev'
Provides-Extra: test
